MANIFEST.in
README.md
setup.py
blog/__init__.py
blog/admin.py
blog/apps.py
blog/feeds.py
blog/forms.py
blog/models.py
blog/search_indexes.py
blog/settings.py
blog/urls.py
blog/views.py
blog/api/__init__.py
blog/api/serializers.py
blog/api/views.py
blog/migrations/0001_initial.py
blog/migrations/__init__.py
blog/static/blog/css/blog.css
blog/static/blog/js/blog.js
blog/templates/blog/_blog_categories.html
blog/templates/blog/_blog_nav_tree.html
blog/templates/blog/_blog_search.html
blog/templates/blog/_tag_cloud.html
blog/templates/blog/all_articles.html
blog/templates/blog/article_archive.html
blog/templates/blog/article_archive_day.html
blog/templates/blog/article_archive_month.html
blog/templates/blog/article_archive_year.html
blog/templates/blog/article_detail.html
blog/templates/blog/article_list.html
blog/templates/blog/base.html
blog/templates/blog/category_detail.html
blog/templates/blog/comments_list.html
blog/templates/blog/rss_feeds.html
blog/templates/blog/search.html
blog/templatetags/__init__.py
blog/templatetags/blog_tags.py
danemco_blog.egg-info/PKG-INFO
danemco_blog.egg-info/SOURCES.txt
danemco_blog.egg-info/dependency_links.txt
danemco_blog.egg-info/pbr.json
danemco_blog.egg-info/requires.txt
danemco_blog.egg-info/top_level.txt
tests/__init__.py
tests/test_api.py
tests/test_no_missing_migrations.py
tests/test_views.py
tests/urls.py