Metadata-Version: 2.1
Name: danemco-blog
Version: 1.8.1
Summary: A fine blog app
Home-page: https://gitlab.com/virgodev/lib/danemco-blog
Author: Danemco, LLC
Author-email: dev@velocitywebworks.com
License: UNKNOWN
Platform: UNKNOWN
